[
  {
    "id": 1,
    "surahNumber": 1,
    "nameArabic": "الفاتحة",
    "nameEnglish": "Al-Fatihah",
    "nameTransliteration": "Al-Fatihah",
    "nameUrdu": "فاتحہ",
    "versesCount": 7,
    "revelationType": "Meccan",
    "orderOfRevelation": 5,
    "descriptionUrdu": "قرآن کی ابتدائی سورت - ام الکتاب",
    "startPageNumber": 37,
    "createdAt": "2026-02-28T03:12:19.220Z"
  },
  {
    "id": 2,
    "surahNumber": 2,
    "nameArabic": "البقرة",
    "nameEnglish": "Al-Baqarah",
    "nameTransliteration": "Al-Baqarah",
    "nameUrdu": "بقرہ",
    "versesCount": 286,
    "revelationType": "Medinan",
    "orderOfRevelation": 87,
    "descriptionUrdu": "قرآن کی سب سے لمبی سورت",
    "startPageNumber": 38,
    "createdAt": "2026-02-28T03:12:19.220Z"
  },
  {
    "id": 3,
    "surahNumber": 3,
    "nameArabic": "آل عمران",
    "nameEnglish": "Al-Imran",
    "nameTransliteration": "Al-Imran",
    "nameUrdu": "آل عمران",
    "versesCount": 200,
    "revelationType": "Medinan",
    "orderOfRevelation": 89,
    "descriptionUrdu": "آل عمران کے بارے میں",
    "startPageNumber": 86,
    "createdAt": "2026-02-28T03:12:19.220Z"
  },
  {
    "id": 4,
    "surahNumber": 4,
    "nameArabic": "النساء",
    "nameEnglish": "An-Nisa",
    "nameTransliteration": "An-Nisa",
    "nameUrdu": "نساء",
    "versesCount": 176,
    "revelationType": "Medinan",
    "orderOfRevelation": 92,
    "descriptionUrdu": "عورتوں کے احکام",
    "startPageNumber": 113,
    "createdAt": "2026-02-28T03:12:19.220Z"
  },
  {
    "id": 5,
    "surahNumber": 5,
    "nameArabic": "المائدة",
    "nameEnglish": "Al-Maidah",
    "nameTransliteration": "Al-Maidah",
    "nameUrdu": "مائدہ",
    "versesCount": 120,
    "revelationType": "Medinan",
    "orderOfRevelation": 112,
    "descriptionUrdu": "دسترخوان کی سورت",
    "startPageNumber": 142,
    "createdAt": "2026-02-28T03:12:19.220Z"
  },
  {
    "id": 6,
    "surahNumber": 6,
    "nameArabic": "الأنعام",
    "nameEnglish": "Al-Anam",
    "nameTransliteration": "Al-Anam",
    "nameUrdu": "انعام",
    "versesCount": 165,
    "revelationType": "Meccan",
    "orderOfRevelation": 55,
    "descriptionUrdu": "مویشیوں کے بارے میں",
    "startPageNumber": 164,
    "createdAt": "2026-02-28T03:12:19.220Z"
  },
  {
    "id": 7,
    "surahNumber": 7,
    "nameArabic": "الأعراف",
    "nameEnglish": "Al-Araf",
    "nameTransliteration": "Al-Araf",
    "nameUrdu": "اعراف",
    "versesCount": 206,
    "revelationType": "Meccan",
    "orderOfRevelation": 39,
    "descriptionUrdu": "اعراف کے لوگوں کا بیان",
    "startPageNumber": 187,
    "createdAt": "2026-02-28T03:12:19.220Z"
  },
  {
    "id": 8,
    "surahNumber": 8,
    "nameArabic": "الأنفال",
    "nameEnglish": "Al-Anfal",
    "nameTransliteration": "Al-Anfal",
    "nameUrdu": "انفال",
    "versesCount": 75,
    "revelationType": "Medinan",
    "orderOfRevelation": 88,
    "descriptionUrdu": "غنیمت کے احکام",
    "startPageNumber": 213,
    "createdAt": "2026-02-28T03:12:19.220Z"
  },
  {
    "id": 9,
    "surahNumber": 9,
    "nameArabic": "التوبة",
    "nameEnglish": "At-Tawbah",
    "nameTransliteration": "At-Tawbah",
    "nameUrdu": "توبہ",
    "versesCount": 129,
    "revelationType": "Medinan",
    "orderOfRevelation": 113,
    "descriptionUrdu": "توبہ اور براءت",
    "startPageNumber": 223,
    "createdAt": "2026-02-28T03:12:19.220Z"
  },
  {
    "id": 10,
    "surahNumber": 10,
    "nameArabic": "يونس",
    "nameEnglish": "Yunus",
    "nameTransliteration": "Yunus",
    "nameUrdu": "یونس",
    "versesCount": 109,
    "revelationType": "Meccan",
    "orderOfRevelation": 51,
    "descriptionUrdu": "حضرت یونس علیہ السلام کا بیان",
    "startPageNumber": 244,
    "createdAt": "2026-02-28T03:12:19.220Z"
  },
  {
    "id": 11,
    "surahNumber": 11,
    "nameArabic": "هود",
    "nameEnglish": "Hud",
    "nameTransliteration": "Hud",
    "nameUrdu": "ہود",
    "versesCount": 123,
    "revelationType": "Meccan",
    "orderOfRevelation": 52,
    "descriptionUrdu": "حضرت ہود علیہ السلام کا بیان",
    "startPageNumber": 257,
    "createdAt": "2026-02-28T03:12:19.220Z"
  },
  {
    "id": 12,
    "surahNumber": 12,
    "nameArabic": "يوسف",
    "nameEnglish": "Yusuf",
    "nameTransliteration": "Yusuf",
    "nameUrdu": "یوسف",
    "versesCount": 111,
    "revelationType": "Meccan",
    "orderOfRevelation": 53,
    "descriptionUrdu": "حضرت یوسف علیہ السلام کا بیان",
    "startPageNumber": 271,
    "createdAt": "2026-02-28T03:12:19.220Z"
  },
  {
    "id": 13,
    "surahNumber": 13,
    "nameArabic": "الرعد",
    "nameEnglish": "Ar-Rad",
    "nameTransliteration": "Ar-Rad",
    "nameUrdu": "رعد",
    "versesCount": 43,
    "revelationType": "Medinan",
    "orderOfRevelation": 96,
    "descriptionUrdu": "گرج کا بیان",
    "startPageNumber": 285,
    "createdAt": "2026-02-28T03:12:19.220Z"
  },
  {
    "id": 14,
    "surahNumber": 14,
    "nameArabic": "إبراهيم",
    "nameEnglish": "Ibrahim",
    "nameTransliteration": "Ibrahim",
    "nameUrdu": "ابراہیم",
    "versesCount": 52,
    "revelationType": "Meccan",
    "orderOfRevelation": 72,
    "descriptionUrdu": "حضرت ابراہیم علیہ السلام کا بیان",
    "startPageNumber": 291,
    "createdAt": "2026-02-28T03:12:19.220Z"
  },
  {
    "id": 15,
    "surahNumber": 15,
    "nameArabic": "الحجر",
    "nameEnglish": "Al-Hijr",
    "nameTransliteration": "Al-Hijr",
    "nameUrdu": "حجر",
    "versesCount": 99,
    "revelationType": "Meccan",
    "orderOfRevelation": 54,
    "descriptionUrdu": "حجر کی وادی کا بیان",
    "startPageNumber": 298,
    "createdAt": "2026-02-28T03:12:19.220Z"
  },
  {
    "id": 16,
    "surahNumber": 16,
    "nameArabic": "النحل",
    "nameEnglish": "An-Nahl",
    "nameTransliteration": "An-Nahl",
    "nameUrdu": "نحل",
    "versesCount": 128,
    "revelationType": "Meccan",
    "orderOfRevelation": 70,
    "descriptionUrdu": "شہد کی مکھی کا بیان",
    "startPageNumber": 303,
    "createdAt": "2026-02-28T03:12:19.220Z"
  },
  {
    "id": 17,
    "surahNumber": 17,
    "nameArabic": "الإسراء",
    "nameEnglish": "Al-Isra",
    "nameTransliteration": "Al-Isra",
    "nameUrdu": "اسراء",
    "versesCount": 111,
    "revelationType": "Meccan",
    "orderOfRevelation": 50,
    "descriptionUrdu": "معراج کا بیان",
    "startPageNumber": 318,
    "createdAt": "2026-02-28T03:12:19.220Z"
  },
  {
    "id": 18,
    "surahNumber": 18,
    "nameArabic": "الكهف",
    "nameEnglish": "Al-Kahf",
    "nameTransliteration": "Al-Kahf",
    "nameUrdu": "کہف",
    "versesCount": 110,
    "revelationType": "Meccan",
    "orderOfRevelation": 69,
    "descriptionUrdu": "غار والوں کا بیان",
    "startPageNumber": 329,
    "createdAt": "2026-02-28T03:12:19.220Z"
  },
  {
    "id": 19,
    "surahNumber": 19,
    "nameArabic": "مريم",
    "nameEnglish": "Maryam",
    "nameTransliteration": "Maryam",
    "nameUrdu": "مریم",
    "versesCount": 98,
    "revelationType": "Meccan",
    "orderOfRevelation": 44,
    "descriptionUrdu": "حضرت مریم علیہا السلام کا بیان",
    "startPageNumber": 341,
    "createdAt": "2026-02-28T03:12:19.220Z"
  },
  {
    "id": 20,
    "surahNumber": 20,
    "nameArabic": "طه",
    "nameEnglish": "Ta-Ha",
    "nameTransliteration": "Ta-Ha",
    "nameUrdu": "طہ",
    "versesCount": 135,
    "revelationType": "Meccan",
    "orderOfRevelation": 45,
    "descriptionUrdu": "طہ کا بیان",
    "startPageNumber": 348,
    "createdAt": "2026-02-28T03:12:19.220Z"
  },
  {
    "id": 21,
    "surahNumber": 21,
    "nameArabic": "الأنبياء",
    "nameEnglish": "Al-Anbiya",
    "nameTransliteration": "Al-Anbiya",
    "nameUrdu": "انبیاء",
    "versesCount": 112,
    "revelationType": "Meccan",
    "orderOfRevelation": 73,
    "descriptionUrdu": "انبیاء کرام کا بیان",
    "startPageNumber": 358,
    "createdAt": "2026-02-28T03:12:19.220Z"
  },
  {
    "id": 22,
    "surahNumber": 22,
    "nameArabic": "الحج",
    "nameEnglish": "Al-Hajj",
    "nameTransliteration": "Al-Hajj",
    "nameUrdu": "حج",
    "versesCount": 78,
    "revelationType": "Medinan",
    "orderOfRevelation": 103,
    "descriptionUrdu": "حج کے احکام",
    "startPageNumber": 368,
    "createdAt": "2026-02-28T03:12:19.220Z"
  },
  {
    "id": 23,
    "surahNumber": 23,
    "nameArabic": "المؤمنون",
    "nameEnglish": "Al-Muminun",
    "nameTransliteration": "Al-Muminun",
    "nameUrdu": "مومنون",
    "versesCount": 118,
    "revelationType": "Meccan",
    "orderOfRevelation": 74,
    "descriptionUrdu": "مومنوں کی صفات",
    "startPageNumber": 378,
    "createdAt": "2026-02-28T03:12:19.220Z"
  },
  {
    "id": 24,
    "surahNumber": 24,
    "nameArabic": "النور",
    "nameEnglish": "An-Nur",
    "nameTransliteration": "An-Nur",
    "nameUrdu": "نور",
    "versesCount": 64,
    "revelationType": "Medinan",
    "orderOfRevelation": 102,
    "descriptionUrdu": "نور کا بیان",
    "startPageNumber": 386,
    "createdAt": "2026-02-28T03:12:19.220Z"
  },
  {
    "id": 25,
    "surahNumber": 25,
    "nameArabic": "الفرقان",
    "nameEnglish": "Al-Furqan",
    "nameTransliteration": "Al-Furqan",
    "nameUrdu": "فرقان",
    "versesCount": 77,
    "revelationType": "Meccan",
    "orderOfRevelation": 42,
    "descriptionUrdu": "حق و باطل کا فرق",
    "startPageNumber": 395,
    "createdAt": "2026-02-28T03:12:19.220Z"
  },
  {
    "id": 26,
    "surahNumber": 26,
    "nameArabic": "الشعراء",
    "nameEnglish": "Ash-Shuara",
    "nameTransliteration": "Ash-Shuara",
    "nameUrdu": "شعراء",
    "versesCount": 227,
    "revelationType": "Meccan",
    "orderOfRevelation": 47,
    "descriptionUrdu": "شاعروں کا بیان",
    "startPageNumber": 403,
    "createdAt": "2026-02-28T03:12:19.220Z"
  },
  {
    "id": 27,
    "surahNumber": 27,
    "nameArabic": "النمل",
    "nameEnglish": "An-Naml",
    "nameTransliteration": "An-Naml",
    "nameUrdu": "نمل",
    "versesCount": 93,
    "revelationType": "Meccan",
    "orderOfRevelation": 48,
    "descriptionUrdu": "چیونٹی کا بیان",
    "startPageNumber": 413,
    "createdAt": "2026-02-28T03:12:19.220Z"
  },
  {
    "id": 28,
    "surahNumber": 28,
    "nameArabic": "القصص",
    "nameEnglish": "Al-Qasas",
    "nameTransliteration": "Al-Qasas",
    "nameUrdu": "قصص",
    "versesCount": 88,
    "revelationType": "Meccan",
    "orderOfRevelation": 49,
    "descriptionUrdu": "قصوں کا بیان",
    "startPageNumber": 421,
    "createdAt": "2026-02-28T03:12:19.220Z"
  },
  {
    "id": 29,
    "surahNumber": 29,
    "nameArabic": "العنكبوت",
    "nameEnglish": "Al-Ankabut",
    "nameTransliteration": "Al-Ankabut",
    "nameUrdu": "عنکبوت",
    "versesCount": 69,
    "revelationType": "Meccan",
    "orderOfRevelation": 85,
    "descriptionUrdu": "مکڑی کا بیان",
    "startPageNumber": 432,
    "createdAt": "2026-02-28T03:12:19.220Z"
  },
  {
    "id": 30,
    "surahNumber": 30,
    "nameArabic": "الروم",
    "nameEnglish": "Ar-Rum",
    "nameTransliteration": "Ar-Rum",
    "nameUrdu": "روم",
    "versesCount": 60,
    "revelationType": "Meccan",
    "orderOfRevelation": 84,
    "descriptionUrdu": "رومیوں کا بیان",
    "startPageNumber": 440,
    "createdAt": "2026-02-28T03:12:19.220Z"
  },
  {
    "id": 31,
    "surahNumber": 31,
    "nameArabic": "لقمان",
    "nameEnglish": "Luqman",
    "nameTransliteration": "Luqman",
    "nameUrdu": "لقمان",
    "versesCount": 34,
    "revelationType": "Meccan",
    "orderOfRevelation": 57,
    "descriptionUrdu": "حضرت لقمان کی حکمت",
    "startPageNumber": 447,
    "createdAt": "2026-02-28T03:12:19.220Z"
  },
  {
    "id": 32,
    "surahNumber": 32,
    "nameArabic": "السجدة",
    "nameEnglish": "As-Sajdah",
    "nameTransliteration": "As-Sajdah",
    "nameUrdu": "سجدہ",
    "versesCount": 30,
    "revelationType": "Meccan",
    "orderOfRevelation": 75,
    "descriptionUrdu": "سجدے کا بیان",
    "startPageNumber": 451,
    "createdAt": "2026-02-28T03:12:19.220Z"
  },
  {
    "id": 33,
    "surahNumber": 33,
    "nameArabic": "الأحزاب",
    "nameEnglish": "Al-Ahzab",
    "nameTransliteration": "Al-Ahzab",
    "nameUrdu": "احزاب",
    "versesCount": 73,
    "revelationType": "Medinan",
    "orderOfRevelation": 90,
    "descriptionUrdu": "لشکروں کا بیان",
    "startPageNumber": 454,
    "createdAt": "2026-02-28T03:12:19.220Z"
  },
  {
    "id": 34,
    "surahNumber": 34,
    "nameArabic": "سبأ",
    "nameEnglish": "Saba",
    "nameTransliteration": "Saba",
    "nameUrdu": "سبا",
    "versesCount": 54,
    "revelationType": "Meccan",
    "orderOfRevelation": 58,
    "descriptionUrdu": "سبا کی قوم کا بیان",
    "startPageNumber": 464,
    "createdAt": "2026-02-28T03:12:19.220Z"
  },
  {
    "id": 35,
    "surahNumber": 35,
    "nameArabic": "فاطر",
    "nameEnglish": "Fatir",
    "nameTransliteration": "Fatir",
    "nameUrdu": "فاطر",
    "versesCount": 45,
    "revelationType": "Meccan",
    "orderOfRevelation": 43,
    "descriptionUrdu": "پیدا کرنے والے کا بیان",
    "startPageNumber": 470,
    "createdAt": "2026-02-28T03:12:19.220Z"
  },
  {
    "id": 36,
    "surahNumber": 36,
    "nameArabic": "يس",
    "nameEnglish": "Ya-Sin",
    "nameTransliteration": "Ya-Sin",
    "nameUrdu": "یٰسین",
    "versesCount": 83,
    "revelationType": "Meccan",
    "orderOfRevelation": 41,
    "descriptionUrdu": "قرآن کا دل",
    "startPageNumber": 476,
    "createdAt": "2026-02-28T03:12:19.220Z"
  },
  {
    "id": 37,
    "surahNumber": 37,
    "nameArabic": "الصافات",
    "nameEnglish": "As-Saffat",
    "nameTransliteration": "As-Saffat",
    "nameUrdu": "صافات",
    "versesCount": 182,
    "revelationType": "Meccan",
    "orderOfRevelation": 56,
    "descriptionUrdu": "صف باندھنے والوں کا بیان",
    "startPageNumber": 482,
    "createdAt": "2026-02-28T03:12:19.220Z"
  },
  {
    "id": 38,
    "surahNumber": 38,
    "nameArabic": "ص",
    "nameEnglish": "Sad",
    "nameTransliteration": "Sad",
    "nameUrdu": "صاد",
    "versesCount": 88,
    "revelationType": "Meccan",
    "orderOfRevelation": 38,
    "descriptionUrdu": "صاد کا بیان",
    "startPageNumber": 489,
    "createdAt": "2026-02-28T03:12:19.220Z"
  },
  {
    "id": 39,
    "surahNumber": 39,
    "nameArabic": "الزمر",
    "nameEnglish": "Az-Zumar",
    "nameTransliteration": "Az-Zumar",
    "nameUrdu": "زمر",
    "versesCount": 75,
    "revelationType": "Meccan",
    "orderOfRevelation": 59,
    "descriptionUrdu": "گروہوں کا بیان",
    "startPageNumber": 494,
    "createdAt": "2026-02-28T03:12:19.220Z"
  },
  {
    "id": 40,
    "surahNumber": 40,
    "nameArabic": "غافر",
    "nameEnglish": "Ghafir",
    "nameTransliteration": "Ghafir",
    "nameUrdu": "غافر",
    "versesCount": 85,
    "revelationType": "Meccan",
    "orderOfRevelation": 60,
    "descriptionUrdu": "معاف کرنے والے کا بیان",
    "startPageNumber": 503,
    "createdAt": "2026-02-28T03:12:19.220Z"
  },
  {
    "id": 41,
    "surahNumber": 41,
    "nameArabic": "فصلت",
    "nameEnglish": "Fussilat",
    "nameTransliteration": "Fussilat",
    "nameUrdu": "فصلت",
    "versesCount": 54,
    "revelationType": "Meccan",
    "orderOfRevelation": 61,
    "descriptionUrdu": "تفصیل کا بیان",
    "startPageNumber": 513,
    "createdAt": "2026-02-28T03:12:19.220Z"
  },
  {
    "id": 42,
    "surahNumber": 42,
    "nameArabic": "الشورى",
    "nameEnglish": "Ash-Shura",
    "nameTransliteration": "Ash-Shura",
    "nameUrdu": "شوریٰ",
    "versesCount": 53,
    "revelationType": "Meccan",
    "orderOfRevelation": 62,
    "descriptionUrdu": "مشاورت کا بیان",
    "startPageNumber": 519,
    "createdAt": "2026-02-28T03:12:19.220Z"
  },
  {
    "id": 43,
    "surahNumber": 43,
    "nameArabic": "الزخرف",
    "nameEnglish": "Az-Zukhruf",
    "nameTransliteration": "Az-Zukhruf",
    "nameUrdu": "زخرف",
    "versesCount": 89,
    "revelationType": "Meccan",
    "orderOfRevelation": 63,
    "descriptionUrdu": "سونے کا بیان",
    "startPageNumber": 525,
    "createdAt": "2026-02-28T03:12:19.220Z"
  },
  {
    "id": 44,
    "surahNumber": 44,
    "nameArabic": "الدخان",
    "nameEnglish": "Ad-Dukhan",
    "nameTransliteration": "Ad-Dukhan",
    "nameUrdu": "دخان",
    "versesCount": 59,
    "revelationType": "Meccan",
    "orderOfRevelation": 64,
    "descriptionUrdu": "دھوئیں کا بیان",
    "startPageNumber": 532,
    "createdAt": "2026-02-28T03:12:19.220Z"
  },
  {
    "id": 45,
    "surahNumber": 45,
    "nameArabic": "الجاثية",
    "nameEnglish": "Al-Jathiyah",
    "nameTransliteration": "Al-Jathiyah",
    "nameUrdu": "جاثیہ",
    "versesCount": 37,
    "revelationType": "Meccan",
    "orderOfRevelation": 65,
    "descriptionUrdu": "گھٹنوں کے بل گرنے کا بیان",
    "startPageNumber": 535,
    "createdAt": "2026-02-28T03:12:19.220Z"
  },
  {
    "id": 46,
    "surahNumber": 46,
    "nameArabic": "الأحقاف",
    "nameEnglish": "Al-Ahqaf",
    "nameTransliteration": "Al-Ahqaf",
    "nameUrdu": "احقاف",
    "versesCount": 35,
    "revelationType": "Meccan",
    "orderOfRevelation": 66,
    "descriptionUrdu": "ریت کے ٹیلوں کا بیان",
    "startPageNumber": 538,
    "createdAt": "2026-02-28T03:12:19.220Z"
  },
  {
    "id": 47,
    "surahNumber": 47,
    "nameArabic": "محمد",
    "nameEnglish": "Muhammad",
    "nameTransliteration": "Muhammad",
    "nameUrdu": "محمد",
    "versesCount": 38,
    "revelationType": "Medinan",
    "orderOfRevelation": 95,
    "descriptionUrdu": "نبی کریم ﷺ کا بیان",
    "startPageNumber": 543,
    "createdAt": "2026-02-28T03:12:19.220Z"
  },
  {
    "id": 48,
    "surahNumber": 48,
    "nameArabic": "الفتح",
    "nameEnglish": "Al-Fath",
    "nameTransliteration": "Al-Fath",
    "nameUrdu": "فتح",
    "versesCount": 29,
    "revelationType": "Medinan",
    "orderOfRevelation": 111,
    "descriptionUrdu": "فتح مکہ کا بیان",
    "startPageNumber": 547,
    "createdAt": "2026-02-28T03:12:19.220Z"
  },
  {
    "id": 49,
    "surahNumber": 49,
    "nameArabic": "الحجرات",
    "nameEnglish": "Al-Hujurat",
    "nameTransliteration": "Al-Hujurat",
    "nameUrdu": "حجرات",
    "versesCount": 18,
    "revelationType": "Medinan",
    "orderOfRevelation": 106,
    "descriptionUrdu": "کمروں کا بیان",
    "startPageNumber": 551,
    "createdAt": "2026-02-28T03:12:19.220Z"
  },
  {
    "id": 50,
    "surahNumber": 50,
    "nameArabic": "ق",
    "nameEnglish": "Qaf",
    "nameTransliteration": "Qaf",
    "nameUrdu": "قاف",
    "versesCount": 45,
    "revelationType": "Meccan",
    "orderOfRevelation": 34,
    "descriptionUrdu": "قاف کا بیان",
    "startPageNumber": 554,
    "createdAt": "2026-02-28T03:12:19.220Z"
  },
  {
    "id": 51,
    "surahNumber": 51,
    "nameArabic": "الذاريات",
    "nameEnglish": "Adh-Dhariyat",
    "nameTransliteration": "Adh-Dhariyat",
    "nameUrdu": "ذاریات",
    "versesCount": 60,
    "revelationType": "Meccan",
    "orderOfRevelation": 67,
    "descriptionUrdu": "بکھیرنے والی ہواؤں کا بیان",
    "startPageNumber": 556,
    "createdAt": "2026-02-28T03:12:19.220Z"
  },
  {
    "id": 52,
    "surahNumber": 52,
    "nameArabic": "الطور",
    "nameEnglish": "At-Tur",
    "nameTransliteration": "At-Tur",
    "nameUrdu": "طور",
    "versesCount": 49,
    "revelationType": "Meccan",
    "orderOfRevelation": 76,
    "descriptionUrdu": "کوہ طور کا بیان",
    "startPageNumber": 559,
    "createdAt": "2026-02-28T03:12:19.220Z"
  },
  {
    "id": 53,
    "surahNumber": 53,
    "nameArabic": "النجم",
    "nameEnglish": "An-Najm",
    "nameTransliteration": "An-Najm",
    "nameUrdu": "نجم",
    "versesCount": 62,
    "revelationType": "Meccan",
    "orderOfRevelation": 23,
    "descriptionUrdu": "ستارے کا بیان",
    "startPageNumber": 562,
    "createdAt": "2026-02-28T03:12:19.220Z"
  },
  {
    "id": 54,
    "surahNumber": 54,
    "nameArabic": "القمر",
    "nameEnglish": "Al-Qamar",
    "nameTransliteration": "Al-Qamar",
    "nameUrdu": "قمر",
    "versesCount": 55,
    "revelationType": "Meccan",
    "orderOfRevelation": 37,
    "descriptionUrdu": "چاند کا بیان",
    "startPageNumber": 564,
    "createdAt": "2026-02-28T03:12:19.220Z"
  },
  {
    "id": 55,
    "surahNumber": 55,
    "nameArabic": "الرحمن",
    "nameEnglish": "Ar-Rahman",
    "nameTransliteration": "Ar-Rahman",
    "nameUrdu": "رحمٰن",
    "versesCount": 78,
    "revelationType": "Medinan",
    "orderOfRevelation": 97,
    "descriptionUrdu": "رحمان کی نعمتوں کا بیان",
    "startPageNumber": 567,
    "createdAt": "2026-02-28T03:12:19.220Z"
  },
  {
    "id": 56,
    "surahNumber": 56,
    "nameArabic": "الواقعة",
    "nameEnglish": "Al-Waqiah",
    "nameTransliteration": "Al-Waqiah",
    "nameUrdu": "واقعہ",
    "versesCount": 96,
    "revelationType": "Meccan",
    "orderOfRevelation": 46,
    "descriptionUrdu": "قیامت کا بیان",
    "startPageNumber": 570,
    "createdAt": "2026-02-28T03:12:19.220Z"
  },
  {
    "id": 57,
    "surahNumber": 57,
    "nameArabic": "الحديد",
    "nameEnglish": "Al-Hadid",
    "nameTransliteration": "Al-Hadid",
    "nameUrdu": "حدید",
    "versesCount": 29,
    "revelationType": "Medinan",
    "orderOfRevelation": 94,
    "descriptionUrdu": "لوہے کا بیان",
    "startPageNumber": 573,
    "createdAt": "2026-02-28T03:12:19.220Z"
  },
  {
    "id": 58,
    "surahNumber": 58,
    "nameArabic": "المجادلة",
    "nameEnglish": "Al-Mujadila",
    "nameTransliteration": "Al-Mujadila",
    "nameUrdu": "مجادلہ",
    "versesCount": 22,
    "revelationType": "Medinan",
    "orderOfRevelation": 105,
    "descriptionUrdu": "بحث کرنے والی کا بیان",
    "startPageNumber": 578,
    "createdAt": "2026-02-28T03:12:19.220Z"
  },
  {
    "id": 59,
    "surahNumber": 59,
    "nameArabic": "الحشر",
    "nameEnglish": "Al-Hashr",
    "nameTransliteration": "Al-Hashr",
    "nameUrdu": "حشر",
    "versesCount": 24,
    "revelationType": "Medinan",
    "orderOfRevelation": 101,
    "descriptionUrdu": "جمع کرنے کا بیان",
    "startPageNumber": 581,
    "createdAt": "2026-02-28T03:12:19.220Z"
  },
  {
    "id": 60,
    "surahNumber": 60,
    "nameArabic": "الممتحنة",
    "nameEnglish": "Al-Mumtahanah",
    "nameTransliteration": "Al-Mumtahanah",
    "nameUrdu": "ممتحنہ",
    "versesCount": 13,
    "revelationType": "Medinan",
    "orderOfRevelation": 91,
    "descriptionUrdu": "آزمائی جانے والی کا بیان",
    "startPageNumber": 585,
    "createdAt": "2026-02-28T03:12:19.220Z"
  },
  {
    "id": 61,
    "surahNumber": 61,
    "nameArabic": "الصف",
    "nameEnglish": "As-Saf",
    "nameTransliteration": "As-Saf",
    "nameUrdu": "صف",
    "versesCount": 14,
    "revelationType": "Medinan",
    "orderOfRevelation": 109,
    "descriptionUrdu": "صف کا بیان",
    "startPageNumber": 587,
    "createdAt": "2026-02-28T03:12:19.220Z"
  },
  {
    "id": 62,
    "surahNumber": 62,
    "nameArabic": "الجمعة",
    "nameEnglish": "Al-Jumuah",
    "nameTransliteration": "Al-Jumuah",
    "nameUrdu": "جمعہ",
    "versesCount": 11,
    "revelationType": "Medinan",
    "orderOfRevelation": 110,
    "descriptionUrdu": "جمعے کا بیان",
    "startPageNumber": 589,
    "createdAt": "2026-02-28T03:12:19.220Z"
  },
  {
    "id": 63,
    "surahNumber": 63,
    "nameArabic": "المنافقون",
    "nameEnglish": "Al-Munafiqun",
    "nameTransliteration": "Al-Munafiqun",
    "nameUrdu": "منافقون",
    "versesCount": 11,
    "revelationType": "Medinan",
    "orderOfRevelation": 104,
    "descriptionUrdu": "منافقوں کا بیان",
    "startPageNumber": 590,
    "createdAt": "2026-02-28T03:12:19.220Z"
  },
  {
    "id": 64,
    "surahNumber": 64,
    "nameArabic": "التغابن",
    "nameEnglish": "At-Taghabun",
    "nameTransliteration": "At-Taghabun",
    "nameUrdu": "تغابن",
    "versesCount": 18,
    "revelationType": "Medinan",
    "orderOfRevelation": 108,
    "descriptionUrdu": "نفع نقصان کا بیان",
    "startPageNumber": 592,
    "createdAt": "2026-02-28T03:12:19.220Z"
  },
  {
    "id": 65,
    "surahNumber": 65,
    "nameArabic": "الطلاق",
    "nameEnglish": "At-Talaq",
    "nameTransliteration": "At-Talaq",
    "nameUrdu": "طلاق",
    "versesCount": 12,
    "revelationType": "Medinan",
    "orderOfRevelation": 99,
    "descriptionUrdu": "طلاق کے احکام",
    "startPageNumber": 594,
    "createdAt": "2026-02-28T03:12:19.220Z"
  },
  {
    "id": 66,
    "surahNumber": 66,
    "nameArabic": "التحريم",
    "nameEnglish": "At-Tahrim",
    "nameTransliteration": "At-Tahrim",
    "nameUrdu": "تحریم",
    "versesCount": 12,
    "revelationType": "Medinan",
    "orderOfRevelation": 107,
    "descriptionUrdu": "حرام کرنے کا بیان",
    "startPageNumber": 596,
    "createdAt": "2026-02-28T03:12:19.220Z"
  },
  {
    "id": 67,
    "surahNumber": 67,
    "nameArabic": "الملك",
    "nameEnglish": "Al-Mulk",
    "nameTransliteration": "Al-Mulk",
    "nameUrdu": "ملک",
    "versesCount": 30,
    "revelationType": "Meccan",
    "orderOfRevelation": 77,
    "descriptionUrdu": "بادشاہت کا بیان",
    "startPageNumber": 598,
    "createdAt": "2026-02-28T03:12:19.220Z"
  },
  {
    "id": 68,
    "surahNumber": 68,
    "nameArabic": "القلم",
    "nameEnglish": "Al-Qalam",
    "nameTransliteration": "Al-Qalam",
    "nameUrdu": "قلم",
    "versesCount": 52,
    "revelationType": "Meccan",
    "orderOfRevelation": 2,
    "descriptionUrdu": "قلم کا بیان",
    "startPageNumber": 600,
    "createdAt": "2026-02-28T03:12:19.220Z"
  },
  {
    "id": 69,
    "surahNumber": 69,
    "nameArabic": "الحاقة",
    "nameEnglish": "Al-Haqqah",
    "nameTransliteration": "Al-Haqqah",
    "nameUrdu": "حاقہ",
    "versesCount": 52,
    "revelationType": "Meccan",
    "orderOfRevelation": 78,
    "descriptionUrdu": "یقینی واقعے کا بیان",
    "startPageNumber": 602,
    "createdAt": "2026-02-28T03:12:19.220Z"
  },
  {
    "id": 70,
    "surahNumber": 70,
    "nameArabic": "المعارج",
    "nameEnglish": "Al-Maarij",
    "nameTransliteration": "Al-Maarij",
    "nameUrdu": "معارج",
    "versesCount": 44,
    "revelationType": "Meccan",
    "orderOfRevelation": 79,
    "descriptionUrdu": "بلندیوں کا بیان",
    "startPageNumber": 604,
    "createdAt": "2026-02-28T03:12:19.220Z"
  },
  {
    "id": 71,
    "surahNumber": 71,
    "nameArabic": "نوح",
    "nameEnglish": "Nuh",
    "nameTransliteration": "Nuh",
    "nameUrdu": "نوح",
    "versesCount": 28,
    "revelationType": "Meccan",
    "orderOfRevelation": 71,
    "descriptionUrdu": "حضرت نوح علیہ السلام کا بیان",
    "startPageNumber": 606,
    "createdAt": "2026-02-28T03:12:19.220Z"
  },
  {
    "id": 72,
    "surahNumber": 72,
    "nameArabic": "الجن",
    "nameEnglish": "Al-Jinn",
    "nameTransliteration": "Al-Jinn",
    "nameUrdu": "جن",
    "versesCount": 28,
    "revelationType": "Meccan",
    "orderOfRevelation": 40,
    "descriptionUrdu": "جنوں کا بیان",
    "startPageNumber": 608,
    "createdAt": "2026-02-28T03:12:19.220Z"
  },
  {
    "id": 73,
    "surahNumber": 73,
    "nameArabic": "المزمل",
    "nameEnglish": "Al-Muzzammil",
    "nameTransliteration": "Al-Muzzammil",
    "nameUrdu": "مزمل",
    "versesCount": 20,
    "revelationType": "Meccan",
    "orderOfRevelation": 3,
    "descriptionUrdu": "کپڑا اوڑھنے والے کا بیان",
    "startPageNumber": 610,
    "createdAt": "2026-02-28T03:12:19.220Z"
  },
  {
    "id": 74,
    "surahNumber": 74,
    "nameArabic": "المدثر",
    "nameEnglish": "Al-Muddaththir",
    "nameTransliteration": "Al-Muddaththir",
    "nameUrdu": "مدثر",
    "versesCount": 56,
    "revelationType": "Meccan",
    "orderOfRevelation": 4,
    "descriptionUrdu": "چادر اوڑھنے والے کا بیان",
    "startPageNumber": 611,
    "createdAt": "2026-02-28T03:12:19.220Z"
  },
  {
    "id": 75,
    "surahNumber": 75,
    "nameArabic": "القيامة",
    "nameEnglish": "Al-Qiyamah",
    "nameTransliteration": "Al-Qiyamah",
    "nameUrdu": "قیامہ",
    "versesCount": 40,
    "revelationType": "Meccan",
    "orderOfRevelation": 31,
    "descriptionUrdu": "قیامت کا بیان",
    "startPageNumber": 613,
    "createdAt": "2026-02-28T03:12:19.220Z"
  },
  {
    "id": 76,
    "surahNumber": 76,
    "nameArabic": "الإنسان",
    "nameEnglish": "Al-Insan",
    "nameTransliteration": "Al-Insan",
    "nameUrdu": "انسان",
    "versesCount": 31,
    "revelationType": "Medinan",
    "orderOfRevelation": 98,
    "descriptionUrdu": "انسان کا بیان",
    "startPageNumber": 614,
    "createdAt": "2026-02-28T03:12:19.220Z"
  },
  {
    "id": 77,
    "surahNumber": 77,
    "nameArabic": "المرسلات",
    "nameEnglish": "Al-Mursalat",
    "nameTransliteration": "Al-Mursalat",
    "nameUrdu": "مرسلات",
    "versesCount": 50,
    "revelationType": "Meccan",
    "orderOfRevelation": 33,
    "descriptionUrdu": "بھیجی گئی ہواؤں کا بیان",
    "startPageNumber": 616,
    "createdAt": "2026-02-28T03:12:19.220Z"
  },
  {
    "id": 78,
    "surahNumber": 78,
    "nameArabic": "النبأ",
    "nameEnglish": "An-Naba",
    "nameTransliteration": "An-Naba",
    "nameUrdu": "نبا",
    "versesCount": 40,
    "revelationType": "Meccan",
    "orderOfRevelation": 80,
    "descriptionUrdu": "خبر کا بیان",
    "startPageNumber": 618,
    "createdAt": "2026-02-28T03:12:19.220Z"
  },
  {
    "id": 79,
    "surahNumber": 79,
    "nameArabic": "النازعات",
    "nameEnglish": "An-Naziat",
    "nameTransliteration": "An-Naziat",
    "nameUrdu": "نازعات",
    "versesCount": 46,
    "revelationType": "Meccan",
    "orderOfRevelation": 81,
    "descriptionUrdu": "کھینچنے والوں کا بیان",
    "startPageNumber": 619,
    "createdAt": "2026-02-28T03:12:19.220Z"
  },
  {
    "id": 80,
    "surahNumber": 80,
    "nameArabic": "عبس",
    "nameEnglish": "Abasa",
    "nameTransliteration": "Abasa",
    "nameUrdu": "عبس",
    "versesCount": 42,
    "revelationType": "Meccan",
    "orderOfRevelation": 24,
    "descriptionUrdu": "چہرہ بسورنے کا بیان",
    "startPageNumber": 621,
    "createdAt": "2026-02-28T03:12:19.220Z"
  },
  {
    "id": 81,
    "surahNumber": 81,
    "nameArabic": "التكوير",
    "nameEnglish": "At-Takwir",
    "nameTransliteration": "At-Takwir",
    "nameUrdu": "تکویر",
    "versesCount": 29,
    "revelationType": "Meccan",
    "orderOfRevelation": 7,
    "descriptionUrdu": "لپیٹنے کا بیان",
    "startPageNumber": 622,
    "createdAt": "2026-02-28T03:12:19.220Z"
  },
  {
    "id": 82,
    "surahNumber": 82,
    "nameArabic": "الإنفطار",
    "nameEnglish": "Al-Infitar",
    "nameTransliteration": "Al-Infitar",
    "nameUrdu": "انفطار",
    "versesCount": 19,
    "revelationType": "Meccan",
    "orderOfRevelation": 82,
    "descriptionUrdu": "پھٹنے کا بیان",
    "startPageNumber": 623,
    "createdAt": "2026-02-28T03:12:19.220Z"
  },
  {
    "id": 83,
    "surahNumber": 83,
    "nameArabic": "المطففين",
    "nameEnglish": "Al-Mutaffifin",
    "nameTransliteration": "Al-Mutaffifin",
    "nameUrdu": "مطففین",
    "versesCount": 36,
    "revelationType": "Meccan",
    "orderOfRevelation": 86,
    "descriptionUrdu": "ناپ تول میں کمی کرنے والوں کا بیان",
    "startPageNumber": 623,
    "createdAt": "2026-02-28T03:12:19.220Z"
  },
  {
    "id": 84,
    "surahNumber": 84,
    "nameArabic": "الإنشقاق",
    "nameEnglish": "Al-Inshiqaq",
    "nameTransliteration": "Al-Inshiqaq",
    "nameUrdu": "انشقاق",
    "versesCount": 25,
    "revelationType": "Meccan",
    "orderOfRevelation": 83,
    "descriptionUrdu": "پھٹنے کا بیان",
    "startPageNumber": 625,
    "createdAt": "2026-02-28T03:12:19.220Z"
  },
  {
    "id": 85,
    "surahNumber": 85,
    "nameArabic": "البروج",
    "nameEnglish": "Al-Buruj",
    "nameTransliteration": "Al-Buruj",
    "nameUrdu": "بروج",
    "versesCount": 22,
    "revelationType": "Meccan",
    "orderOfRevelation": 27,
    "descriptionUrdu": "برجوں کا بیان",
    "startPageNumber": 626,
    "createdAt": "2026-02-28T03:12:19.220Z"
  },
  {
    "id": 86,
    "surahNumber": 86,
    "nameArabic": "الطارق",
    "nameEnglish": "At-Tariq",
    "nameTransliteration": "At-Tariq",
    "nameUrdu": "طارق",
    "versesCount": 17,
    "revelationType": "Meccan",
    "orderOfRevelation": 36,
    "descriptionUrdu": "رات کو آنے والے کا بیان",
    "startPageNumber": 627,
    "createdAt": "2026-02-28T03:12:19.220Z"
  },
  {
    "id": 87,
    "surahNumber": 87,
    "nameArabic": "الأعلى",
    "nameEnglish": "Al-Ala",
    "nameTransliteration": "Al-Ala",
    "nameUrdu": "اعلیٰ",
    "versesCount": 19,
    "revelationType": "Meccan",
    "orderOfRevelation": 8,
    "descriptionUrdu": "سب سے بلند کا بیان",
    "startPageNumber": 627,
    "createdAt": "2026-02-28T03:12:19.220Z"
  },
  {
    "id": 88,
    "surahNumber": 88,
    "nameArabic": "الغاشية",
    "nameEnglish": "Al-Ghashiyah",
    "nameTransliteration": "Al-Ghashiyah",
    "nameUrdu": "غاشیہ",
    "versesCount": 26,
    "revelationType": "Meccan",
    "orderOfRevelation": 68,
    "descriptionUrdu": "ڈھانپ لینے والے کا بیان",
    "startPageNumber": 628,
    "createdAt": "2026-02-28T03:12:19.220Z"
  },
  {
    "id": 89,
    "surahNumber": 89,
    "nameArabic": "الفجر",
    "nameEnglish": "Al-Fajr",
    "nameTransliteration": "Al-Fajr",
    "nameUrdu": "فجر",
    "versesCount": 30,
    "revelationType": "Meccan",
    "orderOfRevelation": 10,
    "descriptionUrdu": "فجر کا بیان",
    "startPageNumber": 629,
    "createdAt": "2026-02-28T03:12:19.220Z"
  },
  {
    "id": 90,
    "surahNumber": 90,
    "nameArabic": "البلد",
    "nameEnglish": "Al-Balad",
    "nameTransliteration": "Al-Balad",
    "nameUrdu": "بلد",
    "versesCount": 20,
    "revelationType": "Meccan",
    "orderOfRevelation": 35,
    "descriptionUrdu": "شہر کا بیان",
    "startPageNumber": 630,
    "createdAt": "2026-02-28T03:12:19.220Z"
  },
  {
    "id": 91,
    "surahNumber": 91,
    "nameArabic": "الشمس",
    "nameEnglish": "Ash-Shams",
    "nameTransliteration": "Ash-Shams",
    "nameUrdu": "شمس",
    "versesCount": 15,
    "revelationType": "Meccan",
    "orderOfRevelation": 26,
    "descriptionUrdu": "سورج کا بیان",
    "startPageNumber": 631,
    "createdAt": "2026-02-28T03:12:19.220Z"
  },
  {
    "id": 92,
    "surahNumber": 92,
    "nameArabic": "الليل",
    "nameEnglish": "Al-Layl",
    "nameTransliteration": "Al-Layl",
    "nameUrdu": "لیل",
    "versesCount": 21,
    "revelationType": "Meccan",
    "orderOfRevelation": 9,
    "descriptionUrdu": "رات کا بیان",
    "startPageNumber": 631,
    "createdAt": "2026-02-28T03:12:19.220Z"
  },
  {
    "id": 93,
    "surahNumber": 93,
    "nameArabic": "الضحى",
    "nameEnglish": "Ad-Duha",
    "nameTransliteration": "Ad-Duha",
    "nameUrdu": "ضحیٰ",
    "versesCount": 11,
    "revelationType": "Meccan",
    "orderOfRevelation": 11,
    "descriptionUrdu": "چاشت کا بیان",
    "startPageNumber": 632,
    "createdAt": "2026-02-28T03:12:19.220Z"
  },
  {
    "id": 94,
    "surahNumber": 94,
    "nameArabic": "الشرح",
    "nameEnglish": "Ash-Sharh",
    "nameTransliteration": "Ash-Sharh",
    "nameUrdu": "شرح",
    "versesCount": 8,
    "revelationType": "Meccan",
    "orderOfRevelation": 12,
    "descriptionUrdu": "سینہ کھولنے کا بیان",
    "startPageNumber": 632,
    "createdAt": "2026-02-28T03:12:19.220Z"
  },
  {
    "id": 95,
    "surahNumber": 95,
    "nameArabic": "التين",
    "nameEnglish": "At-Tin",
    "nameTransliteration": "At-Tin",
    "nameUrdu": "تین",
    "versesCount": 8,
    "revelationType": "Meccan",
    "orderOfRevelation": 28,
    "descriptionUrdu": "انجیر کا بیان",
    "startPageNumber": 633,
    "createdAt": "2026-02-28T03:12:19.220Z"
  },
  {
    "id": 96,
    "surahNumber": 96,
    "nameArabic": "العلق",
    "nameEnglish": "Al-Alaq",
    "nameTransliteration": "Al-Alaq",
    "nameUrdu": "علق",
    "versesCount": 19,
    "revelationType": "Meccan",
    "orderOfRevelation": 1,
    "descriptionUrdu": "خون کے لوتھڑے کا بیان - پہلی وحی",
    "startPageNumber": 633,
    "createdAt": "2026-02-28T03:12:19.220Z"
  },
  {
    "id": 97,
    "surahNumber": 97,
    "nameArabic": "القدر",
    "nameEnglish": "Al-Qadr",
    "nameTransliteration": "Al-Qadr",
    "nameUrdu": "قدر",
    "versesCount": 5,
    "revelationType": "Meccan",
    "orderOfRevelation": 25,
    "descriptionUrdu": "شب قدر کا بیان",
    "startPageNumber": 634,
    "createdAt": "2026-02-28T03:12:19.220Z"
  },
  {
    "id": 98,
    "surahNumber": 98,
    "nameArabic": "البينة",
    "nameEnglish": "Al-Bayyinah",
    "nameTransliteration": "Al-Bayyinah",
    "nameUrdu": "بینہ",
    "versesCount": 8,
    "revelationType": "Medinan",
    "orderOfRevelation": 100,
    "descriptionUrdu": "واضح دلیل کا بیان",
    "startPageNumber": 634,
    "createdAt": "2026-02-28T03:12:19.220Z"
  },
  {
    "id": 99,
    "surahNumber": 99,
    "nameArabic": "الزلزلة",
    "nameEnglish": "Az-Zalzalah",
    "nameTransliteration": "Az-Zalzalah",
    "nameUrdu": "زلزلہ",
    "versesCount": 8,
    "revelationType": "Medinan",
    "orderOfRevelation": 93,
    "descriptionUrdu": "زلزلے کا بیان",
    "startPageNumber": 635,
    "createdAt": "2026-02-28T03:12:19.220Z"
  },
  {
    "id": 100,
    "surahNumber": 100,
    "nameArabic": "العاديات",
    "nameEnglish": "Al-Adiyat",
    "nameTransliteration": "Al-Adiyat",
    "nameUrdu": "عادیات",
    "versesCount": 11,
    "revelationType": "Meccan",
    "orderOfRevelation": 14,
    "descriptionUrdu": "دوڑنے والے گھوڑوں کا بیان",
    "startPageNumber": 635,
    "createdAt": "2026-02-28T03:12:19.220Z"
  },
  {
    "id": 101,
    "surahNumber": 101,
    "nameArabic": "القارعة",
    "nameEnglish": "Al-Qariah",
    "nameTransliteration": "Al-Qariah",
    "nameUrdu": "قارعہ",
    "versesCount": 11,
    "revelationType": "Meccan",
    "orderOfRevelation": 30,
    "descriptionUrdu": "کھٹکھٹانے والے کا بیان",
    "startPageNumber": 636,
    "createdAt": "2026-02-28T03:12:19.220Z"
  },
  {
    "id": 102,
    "surahNumber": 102,
    "nameArabic": "التكاثر",
    "nameEnglish": "At-Takathur",
    "nameTransliteration": "At-Takathur",
    "nameUrdu": "تکاثر",
    "versesCount": 8,
    "revelationType": "Meccan",
    "orderOfRevelation": 16,
    "descriptionUrdu": "زیادتی کی خواہش کا بیان",
    "startPageNumber": 636,
    "createdAt": "2026-02-28T03:12:19.220Z"
  },
  {
    "id": 103,
    "surahNumber": 103,
    "nameArabic": "العصر",
    "nameEnglish": "Al-Asr",
    "nameTransliteration": "Al-Asr",
    "nameUrdu": "عصر",
    "versesCount": 3,
    "revelationType": "Meccan",
    "orderOfRevelation": 13,
    "descriptionUrdu": "زمانے کا بیان",
    "startPageNumber": 637,
    "createdAt": "2026-02-28T03:12:19.220Z"
  },
  {
    "id": 104,
    "surahNumber": 104,
    "nameArabic": "الهمزة",
    "nameEnglish": "Al-Humazah",
    "nameTransliteration": "Al-Humazah",
    "nameUrdu": "ہمزہ",
    "versesCount": 9,
    "revelationType": "Meccan",
    "orderOfRevelation": 32,
    "descriptionUrdu": "چغل خور کا بیان",
    "startPageNumber": 637,
    "createdAt": "2026-02-28T03:12:19.220Z"
  },
  {
    "id": 105,
    "surahNumber": 105,
    "nameArabic": "الفيل",
    "nameEnglish": "Al-Fil",
    "nameTransliteration": "Al-Fil",
    "nameUrdu": "فیل",
    "versesCount": 5,
    "revelationType": "Meccan",
    "orderOfRevelation": 19,
    "descriptionUrdu": "ہاتھی کا بیان",
    "startPageNumber": 637,
    "createdAt": "2026-02-28T03:12:19.220Z"
  },
  {
    "id": 106,
    "surahNumber": 106,
    "nameArabic": "قريش",
    "nameEnglish": "Quraysh",
    "nameTransliteration": "Quraysh",
    "nameUrdu": "قریش",
    "versesCount": 4,
    "revelationType": "Meccan",
    "orderOfRevelation": 29,
    "descriptionUrdu": "قریش کا بیان",
    "startPageNumber": 638,
    "createdAt": "2026-02-28T03:12:19.220Z"
  },
  {
    "id": 107,
    "surahNumber": 107,
    "nameArabic": "الماعون",
    "nameEnglish": "Al-Maun",
    "nameTransliteration": "Al-Maun",
    "nameUrdu": "ماعون",
    "versesCount": 7,
    "revelationType": "Meccan",
    "orderOfRevelation": 17,
    "descriptionUrdu": "برتن دینے کا بیان",
    "startPageNumber": 638,
    "createdAt": "2026-02-28T03:12:19.220Z"
  },
  {
    "id": 108,
    "surahNumber": 108,
    "nameArabic": "الكوثر",
    "nameEnglish": "Al-Kawthar",
    "nameTransliteration": "Al-Kawthar",
    "nameUrdu": "کوثر",
    "versesCount": 3,
    "revelationType": "Meccan",
    "orderOfRevelation": 15,
    "descriptionUrdu": "حوض کوثر کا بیان",
    "startPageNumber": 638,
    "createdAt": "2026-02-28T03:12:19.220Z"
  },
  {
    "id": 109,
    "surahNumber": 109,
    "nameArabic": "الكافرون",
    "nameEnglish": "Al-Kafirun",
    "nameTransliteration": "Al-Kafirun",
    "nameUrdu": "کافرون",
    "versesCount": 6,
    "revelationType": "Meccan",
    "orderOfRevelation": 18,
    "descriptionUrdu": "کافروں کا بیان",
    "startPageNumber": 639,
    "createdAt": "2026-02-28T03:12:19.220Z"
  },
  {
    "id": 110,
    "surahNumber": 110,
    "nameArabic": "النصر",
    "nameEnglish": "An-Nasr",
    "nameTransliteration": "An-Nasr",
    "nameUrdu": "نصر",
    "versesCount": 3,
    "revelationType": "Medinan",
    "orderOfRevelation": 114,
    "descriptionUrdu": "مدد کا بیان",
    "startPageNumber": 639,
    "createdAt": "2026-02-28T03:12:19.220Z"
  },
  {
    "id": 111,
    "surahNumber": 111,
    "nameArabic": "المسد",
    "nameEnglish": "Al-Masad",
    "nameTransliteration": "Al-Masad",
    "nameUrdu": "مسد",
    "versesCount": 5,
    "revelationType": "Meccan",
    "orderOfRevelation": 6,
    "descriptionUrdu": "ابو لہب کا بیان",
    "startPageNumber": 639,
    "createdAt": "2026-02-28T03:12:19.220Z"
  },
  {
    "id": 112,
    "surahNumber": 112,
    "nameArabic": "الإخلاص",
    "nameEnglish": "Al-Ikhlas",
    "nameTransliteration": "Al-Ikhlas",
    "nameUrdu": "اخلاص",
    "versesCount": 4,
    "revelationType": "Meccan",
    "orderOfRevelation": 22,
    "descriptionUrdu": "اللہ کی وحدانیت کا بیان",
    "startPageNumber": 640,
    "createdAt": "2026-02-28T03:12:19.220Z"
  },
  {
    "id": 113,
    "surahNumber": 113,
    "nameArabic": "الفلق",
    "nameEnglish": "Al-Falaq",
    "nameTransliteration": "Al-Falaq",
    "nameUrdu": "فلق",
    "versesCount": 5,
    "revelationType": "Meccan",
    "orderOfRevelation": 20,
    "descriptionUrdu": "صبح کا بیان",
    "startPageNumber": 640,
    "createdAt": "2026-02-28T03:12:19.220Z"
  },
  {
    "id": 114,
    "surahNumber": 114,
    "nameArabic": "الناس",
    "nameEnglish": "An-Nas",
    "nameTransliteration": "An-Nas",
    "nameUrdu": "ناس",
    "versesCount": 6,
    "revelationType": "Meccan",
    "orderOfRevelation": 21,
    "descriptionUrdu": "لوگوں کا بیان",
    "startPageNumber": 640,
    "createdAt": "2026-02-28T03:12:19.220Z"
  }
]